llm_lab/__init__.py
llm_lab/agent/__init__.py
llm_lab/agent/agent.py
llm_lab/agent/litellm_http.py
llm_lab/agent/llm_client.py
llm_lab/exceptions/__init__.py
llm_lab/exceptions/base.py
llm_lab/exceptions/config.py
llm_lab/filetextio/__init__.py
llm_lab/filetextio/parsers.py
llm_lab/logging/__init__.py
llm_lab/logging/logger.py
llm_lab/preprocessing/__init__.py
llm_lab/preprocessing/text_normalization.py
tokens_lab-0.2.7.dist-info/METADATA
tokens_lab-0.2.7.dist-info/WHEEL
tokens_lab-0.2.7.dist-info/top_level.txt
tokens_lab-0.2.7.dist-info/RECORD
