Metadata-Version: 2.4
Name: tokens-lab
Version: 0.2.7
Summary: LLM utilities with agents, file parsing, and preprocessing built in.
Author: Youssef Moussallem
Author-email: Mohamed Moslemani <moslemanomohamed@gmail.com>
License: MIT
Project-URL: Homepage, https://github.com/mohamed-moslemani/LLM_Lab
Project-URL: Repository, https://github.com/mohamed-moslemani/LLM_Lab
Project-URL: Issues, https://github.com/mohamed-moslemani/LLM_Lab/issues
Keywords: llm,agents,rag,langchain,llm-tools
Classifier: Programming Language :: Python :: 3
Classifier: Typing :: Typed
Classifier: Operating System :: OS Independent
Requires-Python: >=3.10
Requires-Dist: langgraph>=0.2.0
Requires-Dist: typing-extensions>=4.8.0
Requires-Dist: openai<3,>=2.13
Requires-Dist: langchain<2,>=0.3.27
Requires-Dist: langchain-text-splitters<2,>=0.3.11
Requires-Dist: langchain-experimental<1,>=0.4.1
Requires-Dist: pdfplumber>=0.11.0
Requires-Dist: python-docx>=1.0.0
Requires-Dist: python-pptx>=0.6.21
Requires-Dist: pypdfium2>=4.0.0
Requires-Dist: pdf2image>=1.16.0
Requires-Dist: Pillow>=9.0.0
